createpass/__init__.py
createpass/createpass.py
createpassword-1.0.2.dist-info/LICENSE
createpassword-1.0.2.dist-info/METADATA
createpassword-1.0.2.dist-info/WHEEL
createpassword-1.0.2.dist-info/top_level.txt
createpassword-1.0.2.dist-info/RECORD
