Metadata-Version: 2.1
Name: createpassword
Version: 1.0.2
Summary: createpassword can automatically create passwords
License: MIT
License-File: LICENSE
Requires-Dist: genepass (==0.1.5)
